{"response": {"total": "292", "dateFormat": "YYYY-MM-DD\"T\"HH24", "frequency": "hourly", "data": [{"period": "2024-10-17T00", "respondent": "PJM", "respondent-name": "PJM Interconnection, LLC", "type": "D", "type-name": "Demand", "value": "90256", "value-units": "megawatthours"}, {"period": "2024-10-17T00", "respondent": "PJM", "respondent-name": "PJM Interconnection, LLC", "type": "DF", "type-name": "Day-ahead demand forecast", "value": "89387", "value-units": "megawatthours"}, {"period": "2024-10-17T00", "respondent": "PJM", "respondent-name": "PJM Interconnection, LLC", "type": "NG", "type-name": "Net generation", "value": "87627", "value-units": "megawatthours"}, {"period": "2024-10-17T00", "respondent": "PJM", "respondent-name": "PJM Interconnection, LLC", "type": "TI", "type-name": "Total interchange", "value": "-2622", "value-units": "megawatthours"}, {"period": "2024-10-17T01", "respondent": "PJM", "respondent-name": "PJM Interconnection, LLC", "type": "D", "type-name": "Demand", "value": "89248", "value-units": "megawatthours"}, {"period": "2024-10-17T01", "respondent": "PJM", "respondent-name": "PJM Interconnection, LLC", "type": "DF", "type-name": "Day-ahead demand forecast", "value": "87519", "value-units": "megawatthours"}, {"period": "2024-10-17T01", "respondent": "PJM", "respondent-name": "PJM Interconnection, LLC", "type": "NG", "type-name": "Net generation", "value": "87122", "value-units": "megawatthours"}, {"period": "2024-10-17T01", "respondent": "PJM", "respondent-name": "PJM Interconnection, LLC", "type": "TI", "type-name": "Total interchange", "value": "-2119", "value-units": "megawatthours"}, {"period": "2024-10-17T02", "respondent": "PJM", "respondent-name": "PJM Interconnection, LLC", "type": "D", "type-name": "Demand", "value": "86764", "value-units": "megawatthours"}, {"period": "2024-10-17T02", "respondent": "PJM", "respondent-name": "PJM Interconnection, LLC", "type": "DF", "type-name": "Day-ahead demand forecast", "value": "83599", "value-units": "megawatthours"}, {"period": "2024-10-17T02", "respondent": "PJM", "respondent-name": "PJM Interconnection, LLC", "type": "NG", "type-name": "Net generation", "value": "84681", "value-units": "megawatthours"}, {"period": "2024-10-17T02", "respondent": "PJM", "respondent-name": "PJM Interconnection, LLC", "type": "TI", "type-name": "Total interchange", "value": "-2076", "value-units": "megawatthours"}, {"period": "2024-10-17T03", "respondent": "PJM", "respondent-name": "PJM Interconnection, LLC", "type": "D", "type-name": "Demand", "value": "82734", "value-units": "megawatthours"}, {"period": "2024-10-17T03", "respondent": "PJM", "respondent-name": "PJM Interconnection, LLC", "type": "DF", "type-name": "Day-ahead demand forecast", "value": "79766", "value-units": "megawatthours"}, {"period": "2024-10-17T03", "respondent": "PJM", "respondent-name": "PJM Interconnection, LLC", "type": "NG", "type-name": "Net generation", "value": "80837", "value-units": "megawatthours"}, {"period": "2024-10-17T03", "respondent": "PJM", "respondent-name": "PJM Interconnection, LLC", "type": "TI", "type-name": "Total interchange", "value": "-1889", "value-units": "megawatthours"}, {"period": "2024-10-17T04", "respondent": "PJM", "respondent-name": "PJM Interconnection, LLC", "type": "D", "type-name": "Demand", "value": "79318", "value-units": "megawatthours"}, {"period": "2024-10-17T04", "respondent": "PJM", "respondent-name": "PJM Interconnection, LLC", "type": "DF", "type-name": "Day-ahead demand forecast", "value": "76614", "value-units": "megawatthours"}, {"period": "2024-10-17T04", "respondent": "PJM", "respondent-name": "PJM Interconnection, LLC", "type": "NG", "type-name": "Net generation", "value": "77973", "value-units": "megawatthours"}, {"period": "2024-10-17T04", "respondent": "PJM", "respondent-name": "PJM Interconnection, LLC", "type": "TI", "type-name": "Total interchange", "value": "-1337", "value-units": "megawatthours"}, {"period": "2024-10-17T05", "respondent": "PJM", "respondent-name": "PJM Interconnection, LLC", "type": "D", "type-name": "Demand", "value": "76645", "value-units": "megawatthours"}, {"period": "2024-10-17T05", "respondent": "PJM", "respondent-name": "PJM Interconnection, LLC", "type": "DF", "type-name": "Day-ahead demand forecast", "value": "74463", "value-units": "megawatthours"}, {"period": "2024-10-17T05", "respondent": "PJM", "respondent-name": "PJM Interconnection, LLC", "type": "NG", "type-name": "Net generation", "value": "76163", "value-units": "megawatthours"}, {"period": "2024-10-17T05", "respondent": "PJM", "respondent-name": "PJM Interconnection, LLC", "type": "TI", "type-name": "Total interchange", "value": "-474", "value-units": "megawatthours"}, {"period": "2024-10-17T06", "respondent": "PJM", "respondent-name": "PJM Interconnection, LLC", "type": "D", "type-name": "Demand", "value": "75303", "value-units": "megawatthours"}, {"period": "2024-10-17T06", "respondent": "PJM", "respondent-name": "PJM Interconnection, LLC", "type": "DF", "type-name": "Day-ahead demand forecast", "value": "73919", "value-units": "megawatthours"}, {"period": "2024-10-17T06", "respondent": "PJM", "respondent-name": "PJM Interconnection, LLC", "type": "NG", "type-name": "Net generation", "value": "73838", "value-units": "megawatthours"}, {"period": "2024-10-17T06", "respondent": "PJM", "respondent-name": "PJM Interconnection, LLC", "type": "TI", "type-name": "Total interchange", "value": "-1461", "value-units": "megawatthours"}, {"period": "2024-10-17T07", "respondent": "PJM", "respondent-name": "PJM Interconnection, LLC", "type": "D", "type-name": "Demand", "value": "75020", "value-units": "megawatthours"}, {"period": "2024-10-17T07", "respondent": "PJM", "respondent-name": "PJM Interconnection, LLC", "type": "DF", "type-name": "Day-ahead demand forecast", "value": "74161", "value-units": "megawatthours"}, {"period": "2024-10-17T07", "respondent": "PJM", "respondent-name": "PJM Interconnection, LLC", "type": "NG", "type-name": "Net generation", "value": "73187", "value-units": "megawatthours"}, {"period": "2024-10-17T07", "respondent": "PJM", "respondent-name": "PJM Interconnection, LLC", "type": "TI", "type-name": "Total interchange", "value": "-1829", "value-units": "megawatthours"}, {"period": "2024-10-17T08", "respondent": "PJM", "respondent-name": "PJM Interconnection, LLC", "type": "D", "type-name": "Demand", "value": "75032", "value-units": "megawatthours"}, {"period": "2024-10-17T08", "respondent": "PJM", "respondent-name": "PJM Interconnection, LLC", "type": "DF", "type-name": "Day-ahead demand forecast", "value": "75941", "value-units": "megawatthours"}, {"period": "2024-10-17T08", "respondent": "PJM", "respondent-name": "PJM Interconnection, LLC", "type": "NG", "type-name": "Net generation", "value": "73371", "value-units": "megawatthours"}, {"period": "2024-10-17T08", "respondent": "PJM", "respondent-name": "PJM Interconnection, LLC", "type": "TI", "type-name": "Total interchange", "value": "-1655", "value-units": "megawatthours"}, {"period": "2024-10-17T09", "respondent": "PJM", "respondent-name": "PJM Interconnection, LLC", "type": "D", "type-name": "Demand", "value": "76165", "value-units": "megawatthours"}, {"period": "2024-10-17T09", "respondent": "PJM", "respondent-name": "PJM Interconnection, LLC", "type": "DF", "type-name": "Day-ahead demand forecast", "value": "80321", "value-units": "megawatthours"}, {"period": "2024-10-17T09", "respondent": "PJM", "respondent-name": "PJM Interconnection, LLC", "type": "NG", "type-name": "Net generation", "value": "74543", "value-units": "megawatthours"}, {"period": "2024-10-17T09", "respondent": "PJM", "respondent-name": "PJM Interconnection, LLC", "type": "TI", "type-name": "Total interchange", "value": "-1616", "value-units": "megawatthours"}, {"period": "2024-10-17T10", "respondent": "PJM", "respondent-name": "PJM Interconnection, LLC", "type": "D", "type-name": "Demand", "value": "80079", "value-units": "megawatthours"}, {"period": "2024-10-17T10", "respondent": "PJM", "respondent-name": "PJM Interconnection, LLC", "type": "DF", "type-name": "Day-ahead demand forecast", "value": "86992", "value-units": "megawatthours"}, {"period": "2024-10-17T10", "respondent": "PJM", "respondent-name": "PJM Interconnection, LLC", "type": "NG", "type-name": "Net generation", "value": "77243", "value-units": "megawatthours"}, {"period": "2024-10-17T10", "respondent": "PJM", "respondent-name": "PJM Interconnection, LLC", "type": "TI", "type-name": "Total interchange", "value": "-2832", "value-units": "megawatthours"}, {"period": "2024-10-17T11", "respondent": "PJM", "respondent-name": "PJM Interconnection, LLC", "type": "D", "type-name": "Demand", "value": "86931", "value-units": "megawatthours"}, {"period": "2024-10-17T11", "respondent": "PJM", "respondent-name": "PJM Interconnection, LLC", "type": "DF", "type-name": "Day-ahead demand forecast", "value": "90882", "value-units": "megawatthours"}, {"period": "2024-10-17T11", "respondent": "PJM", "respondent-name": "PJM Interconnection, LLC", "type": "NG", "type-name": "Net generation", "value": "83098", "value-units": "megawatthours"}, {"period": "2024-10-17T11", "respondent": "PJM", "respondent-name": "PJM Interconnection, LLC", "type": "TI", "type-name": "Total interchange", "value": "-3827", "value-units": "megawatthours"}, {"period": "2024-10-17T12", "respondent": "PJM", "respondent-name": "PJM Interconnection, LLC", "type": "D", "type-name": "Demand", "value": "91728", "value-units": "megawatthours"}, {"period": "2024-10-17T12", "respondent": "PJM", "respondent-name": "PJM Interconnection, LLC", "type": "DF", "type-name": "Day-ahead demand forecast", "value": "90332", "value-units": "megawatthours"}, {"period": "2024-10-17T12", "respondent": "PJM", "respondent-name": "PJM Interconnection, LLC", "type": "NG", "type-name": "Net generation", "value": "89091", "value-units": "megawatthours"}, {"period": "2024-10-17T12", "respondent": "PJM", "respondent-name": "PJM Interconnection, LLC", "type": "TI", "type-name": "Total interchange", "value": "-2629", "value-units": "megawatthours"}, {"period": "2024-10-17T13", "respondent": "PJM", "respondent-name": "PJM Interconnection, LLC", "type": "D", "type-name": "Demand", "value": "92055", "value-units": "megawatthours"}, {"period": "2024-10-17T13", "respondent": "PJM", "respondent-name": "PJM Interconnection, LLC", "type": "DF", "type-name": "Day-ahead demand forecast", "value": "87772", "value-units": "megawatthours"}, {"period": "2024-10-17T13", "respondent": "PJM", "respondent-name": "PJM Interconnection, LLC", "type": "NG", "type-name": "Net generation", "value": "90597", "value-units": "megawatthours"}, {"period": "2024-10-17T13", "respondent": "PJM", "respondent-name": "PJM Interconnection, LLC", "type": "TI", "type-name": "Total interchange", "value": "-1452", "value-units": "megawatthours"}, {"period": "2024-10-17T14", "respondent": "PJM", "respondent-name": "PJM Interconnection, LLC", "type": "D", "type-name": "Demand", "value": "89009", "value-units": "megawatthours"}, {"period": "2024-10-17T14", "respondent": "PJM", "respondent-name": "PJM Interconnection, LLC", "type": "DF", "type-name": "Day-ahead demand forecast", "value": "85611", "value-units": "megawatthours"}, {"period": "2024-10-17T14", "respondent": "PJM", "respondent-name": "PJM Interconnection, LLC", "type": "NG", "type-name": "Net generation", "value": "88423", "value-units": "megawatthours"}, {"period": "2024-10-17T14", "respondent": "PJM", "respondent-name": "PJM Interconnection, LLC", "type": "TI", "type-name": "Total interchange", "value": "-582", "value-units": "megawatthours"}, {"period": "2024-10-17T15", "respondent": "PJM", "respondent-name": "PJM Interconnection, LLC", "type": "D", "type-name": "Demand", "value": "86187", "value-units": "megawatthours"}, {"period": "2024-10-17T15", "respondent": "PJM", "respondent-name": "PJM Interconnection, LLC", "type": "DF", "type-name": "Day-ahead demand forecast", "value": "83976", "value-units": "megawatthours"}, {"period": "2024-10-17T15", "respondent": "PJM", "respondent-name": "PJM Interconnection, LLC", "type": "NG", "type-name": "Net generation", "value": "85551", "value-units": "megawatthours"}, {"period": "2024-10-17T15", "respondent": "PJM", "respondent-name": "PJM Interconnection, LLC", "type": "TI", "type-name": "Total interchange", "value": "-631", "value-units": "megawatthours"}, {"period": "2024-10-17T16", "respondent": "PJM", "respondent-name": "PJM Interconnection, LLC", "type": "D", "type-name": "Demand", "value": "84335", "value-units": "megawatthours"}, {"period": "2024-10-17T16", "respondent": "PJM", "respondent-name": "PJM Interconnection, LLC", "type": "DF", "type-name": "Day-ahead demand forecast", "value": "82781", "value-units": "megawatthours"}, {"period": "2024-10-17T16", "respondent": "PJM", "respondent-name": "PJM Interconnection, LLC", "type": "NG", "type-name": "Net generation", "value": "82703", "value-units": "megawatthours"}, {"period": "2024-10-17T16", "respondent": "PJM", "respondent-name": "PJM Interconnection, LLC", "type": "TI", "type-name": "Total interchange", "value": "-1629", "value-units": "megawatthours"}, {"period": "2024-10-17T17", "respondent": "PJM", "respondent-name": "PJM Interconnection, LLC", "type": "D", "type-name": "Demand", "value": "83613", "value-units": "megawatthours"}, {"period": "2024-10-17T17", "respondent": "PJM", "respondent-name": "PJM Interconnection, LLC", "type": "DF", "type-name": "Day-ahead demand forecast", "value": "82289", "value-units": "megawatthours"}, {"period": "2024-10-17T17", "respondent": "PJM", "respondent-name": "PJM Interconnection, LLC", "type": "NG", "type-name": "Net generation", "value": "82460", "value-units": "megawatthours"}, {"period": "2024-10-17T17", "respondent": "PJM", "respondent-name": "PJM Interconnection, LLC", "type": "TI", "type-name": "Total interchange", "value": "-1150", "value-units": "megawatthours"}, {"period": "2024-10-17T18", "respondent": "PJM", "respondent-name": "PJM Interconnection, LLC", "type": "D", "type-name": "Demand", "value": "83034", "value-units": "megawatthours"}, {"period": "2024-10-17T18", "respondent": "PJM", "respondent-name": "PJM Interconnection, LLC", "type": "DF", "type-name": "Day-ahead demand forecast", "value": "81754", "value-units": "megawatthours"}, {"period": "2024-10-17T18", "respondent": "PJM", "respondent-name": "PJM Interconnection, LLC", "type": "NG", "type-name": "Net generation", "value": "81878", "value-units": "megawatthours"}, {"period": "2024-10-17T18", "respondent": "PJM", "respondent-name": "PJM Interconnection, LLC", "type": "TI", "type-name": "Total interchange", "value": "-1153", "value-units": "megawatthours"}, {"period": "2024-10-17T19", "respondent": "PJM", "respondent-name": "PJM Interconnection, LLC", "type": "D", "type-name": "Demand", "value": "82194", "value-units": "megawatthours"}, {"period": "2024-10-17T19", "respondent": "PJM", "respondent-name": "PJM Interconnection, LLC", "type": "DF", "type-name": "Day-ahead demand forecast", "value": "81612", "value-units": "megawatthours"}, {"period": "2024-10-17T19", "respondent": "PJM", "respondent-name": "PJM Interconnection, LLC", "type": "NG", "type-name": "Net generation", "value": "81315", "value-units": "megawatthours"}, {"period": "2024-10-17T19", "respondent": "PJM", "respondent-name": "PJM Interconnection, LLC", "type": "TI", "type-name": "Total interchange", "value": "-876", "value-units": "megawatthours"}, {"period": "2024-10-17T20", "respondent": "PJM", "respondent-name": "PJM Interconnection, LLC", "type": "D", "type-name": "Demand", "value": "82095", "value-units": "megawatthours"}, {"period": "2024-10-17T20", "respondent": "PJM", "respondent-name": "PJM Interconnection, LLC", "type": "DF", "type-name": "Day-ahead demand forecast", "value": "82566", "value-units": "megawatthours"}, {"period": "2024-10-17T20", "respondent": "PJM", "respondent-name": "PJM Interconnection, LLC", "type": "NG", "type-name": "Net generation", "value": "81670", "value-units": "megawatthours"}, {"period": "2024-10-17T20", "respondent": "PJM", "respondent-name": "PJM Interconnection, LLC", "type": "TI", "type-name": "Total interchange", "value": "-423", "value-units": "megawatthours"}, {"period": "2024-10-17T21", "respondent": "PJM", "respondent-name": "PJM Interconnection, LLC", "type": "D", "type-name": "Demand", "value": "82769", "value-units": "megawatthours"}, {"period": "2024-10-17T21", "respondent": "PJM", "respondent-name": "PJM Interconnection, LLC", "type": "DF", "type-name": "Day-ahead demand forecast", "value": "84176", "value-units": "megawatthours"}, {"period": "2024-10-17T21", "respondent": "PJM", "respondent-name": "PJM Interconnection, LLC", "type": "NG", "type-name": "Net generation", "value": "81870", "value-units": "megawatthours"}, {"period": "2024-10-17T21", "respondent": "PJM", "respondent-name": "PJM Interconnection, LLC", "type": "TI", "type-name": "Total interchange", "value": "-896", "value-units": "megawatthours"}, {"period": "2024-10-17T22", "respondent": "PJM", "respondent-name": "PJM Interconnection, LLC", "type": "D", "type-name": "Demand", "value": "84163", "value-units": "megawatthours"}, {"period": "2024-10-17T22", "respondent": "PJM", "respondent-name": "PJM Interconnection, LLC", "type": "DF", "type-name": "Day-ahead demand forecast", "value": "85608", "value-units": "megawatthours"}, {"period": "2024-10-17T22", "respondent": "PJM", "respondent-name": "PJM Interconnection, LLC", "type": "NG", "type-name": "Net generation", "value": "82335", "value-units": "megawatthours"}, {"period": "2024-10-17T22", "respondent": "PJM", "respondent-name": "PJM Interconnection, LLC", "type": "TI", "type-name": "Total interchange", "value": "-1824", "value-units": "megawatthours"}, {"period": "2024-10-17T23", "respondent": "PJM", "respondent-name": "PJM Interconnection, LLC", "type": "D", "type-name": "Demand", "value": "86526", "value-units": "megawatthours"}, {"period": "2024-10-17T23", "respondent": "PJM", "respondent-name": "PJM Interconnection, LLC", "type": "DF", "type-name": "Day-ahead demand forecast", "value": "87220", "value-units": "megawatthours"}, {"period": "2024-10-17T23", "respondent": "PJM", "respondent-name": "PJM Interconnection, LLC", "type": "NG", "type-name": "Net generation", "value": "83685", "value-units": "megawatthours"}, {"period": "2024-10-17T23", "respondent": "PJM", "respondent-name": "PJM Interconnection, LLC", "type": "TI", "type-name": "Total interchange", "value": "-2835", "value-units": "megawatthours"}, {"period": "2024-10-18T00", "respondent": "PJM", "respondent-name": "PJM Interconnection, LLC", "type": "D", "type-name": "Demand", "value": "88834", "value-units": "megawatthours"}, {"period": "2024-10-18T00", "respondent": "PJM", "respondent-name": "PJM Interconnection, LLC", "type": "DF", "type-name": "Day-ahead demand forecast", "value": "88108", "value-units": "megawatthours"}, {"period": "2024-10-18T00", "respondent": "PJM", "respondent-name": "PJM Interconnection, LLC", "type": "NG", "type-name": "Net generation", "value": "86762", "value-units": "megawatthours"}, {"period": "2024-10-18T00", "respondent": "PJM", "respondent-name": "PJM Interconnection, LLC", "type": "TI", "type-name": "Total interchange", "value": "-2066", "value-units": "megawatthours"}, {"period": "2024-10-18T01", "respondent": "PJM", "respondent-name": "PJM Interconnection, LLC", "type": "D", "type-name": "Demand", "value": "87837", "value-units": "megawatthours"}, {"period": "2024-10-18T01", "respondent": "PJM", "respondent-name": "PJM Interconnection, LLC", "type": "DF", "type-name": "Day-ahead demand forecast", "value": "86200", "value-units": "megawatthours"}, {"period": "2024-10-18T01", "respondent": "PJM", "respondent-name": "PJM Interconnection, LLC", "type": "NG", "type-name": "Net generation", "value": "85745", "value-units": "megawatthours"}, {"period": "2024-10-18T01", "respondent": "PJM", "respondent-name": "PJM Interconnection, LLC", "type": "TI", "type-name": "Total interchange", "value": "-2088", "value-units": "megawatthours"}, {"period": "2024-10-18T02", "respondent": "PJM", "respondent-name": "PJM Interconnection, LLC", "type": "D", "type-name": "Demand", "value": "85677", "value-units": "megawatthours"}, {"period": "2024-10-18T02", "respondent": "PJM", "respondent-name": "PJM Interconnection, LLC", "type": "DF", "type-name": "Day-ahead demand forecast", "value": "82312", "value-units": "megawatthours"}, {"period": "2024-10-18T02", "respondent": "PJM", "respondent-name": "PJM Interconnection, LLC", "type": "NG", "type-name": "Net generation", "value": "83983", "value-units": "megawatthours"}, {"period": "2024-10-18T02", "respondent": "PJM", "respondent-name": "PJM Interconnection, LLC", "type": "TI", "type-name": "Total interchange", "value": "-1688", "value-units": "megawatthours"}, {"period": "2024-10-18T03", "respondent": "PJM", "respondent-name": "PJM Interconnection, LLC", "type": "D", "type-name": "Demand", "value": "81938", "value-units": "megawatthours"}, {"period": "2024-10-18T03", "respondent": "PJM", "respondent-name": "PJM Interconnection, LLC", "type": "DF", "type-name": "Day-ahead demand forecast", "value": "78410", "value-units": "megawatthours"}, {"period": "2024-10-18T03", "respondent": "PJM", "respondent-name": "PJM Interconnection, LLC", "type": "NG", "type-name": "Net generation", "value": "80261", "value-units": "megawatthours"}, {"period": "2024-10-18T03", "respondent": "PJM", "respondent-name": "PJM Interconnection, LLC", "type": "TI", "type-name": "Total interchange", "value": "-1672", "value-units": "megawatthours"}, {"period": "2024-10-18T04", "respondent": "PJM", "respondent-name": "PJM Interconnection, LLC", "type": "D", "type-name": "Demand", "value": "78789", "value-units": "megawatthours"}, {"period": "2024-10-18T04", "respondent": "PJM", "respondent-name": "PJM Interconnection, LLC", "type": "DF", "type-name": "Day-ahead demand forecast", "value": "75201", "value-units": "megawatthours"}, {"period": "2024-10-18T04", "respondent": "PJM", "respondent-name": "PJM Interconnection, LLC", "type": "NG", "type-name": "Net generation", "value": "77263", "value-units": "megawatthours"}, {"period": "2024-10-18T04", "respondent": "PJM", "respondent-name": "PJM Interconnection, LLC", "type": "TI", "type-name": "Total interchange", "value": "-1522", "value-units": "megawatthours"}, {"period": "2024-10-18T05", "respondent": "PJM", "respondent-name": "PJM Interconnection, LLC", "type": "D", "type-name": "Demand", "value": "76071", "value-units": "megawatthours"}, {"period": "2024-10-18T05", "respondent": "PJM", "respondent-name": "PJM Interconnection, LLC", "type": "DF", "type-name": "Day-ahead demand forecast", "value": "73203", "value-units": "megawatthours"}, {"period": "2024-10-18T05", "respondent": "PJM", "respondent-name": "PJM Interconnection, LLC", "type": "NG", "type-name": "Net generation", "value": "75784", "value-units": "megawatthours"}, {"period": "2024-10-18T05", "respondent": "PJM", "respondent-name": "PJM Interconnection, LLC", "type": "TI", "type-name": "Total interchange", "value": "-283", "value-units": "megawatthours"}, {"period": "2024-10-18T06", "respondent": "PJM", "respondent-name": "PJM Interconnection, LLC", "type": "D", "type-name": "Demand", "value": "75262", "value-units": "megawatthours"}, {"period": "2024-10-18T06", "respondent": "PJM", "respondent-name": "PJM Interconnection, LLC", "type": "DF", "type-name": "Day-ahead demand forecast", "value": "72589", "value-units": "megawatthours"}, {"period": "2024-10-18T06", "respondent": "PJM", "respondent-name": "PJM Interconnection, LLC", "type": "NG", "type-name": "Net generation", "value": "75049", "value-units": "megawatthours"}, {"period": "2024-10-18T06", "respondent": "PJM", "respondent-name": "PJM Interconnection, LLC", "type": "TI", "type-name": "Total interchange", "value": "-210", "value-units": "megawatthours"}, {"period": "2024-10-18T07", "respondent": "PJM", "respondent-name": "PJM Interconnection, LLC", "type": "D", "type-name": "Demand", "value": "74495", "value-units": "megawatthours"}, {"period": "2024-10-18T07", "respondent": "PJM", "respondent-name": "PJM Interconnection, LLC", "type": "DF", "type-name": "Day-ahead demand forecast", "value": "72787", "value-units": "megawatthours"}, {"period": "2024-10-18T07", "respondent": "PJM", "respondent-name": "PJM Interconnection, LLC", "type": "NG", "type-name": "Net generation", "value": "74202", "value-units": "megawatthours"}, {"period": "2024-10-18T07", "respondent": "PJM", "respondent-name": "PJM Interconnection, LLC", "type": "TI", "type-name": "Total interchange", "value": "-291", "value-units": "megawatthours"}, {"period": "2024-10-18T08", "respondent": "PJM", "respondent-name": "PJM Interconnection, LLC", "type": "D", "type-name": "Demand", "value": "74518", "value-units": "megawatthours"}, {"period": "2024-10-18T08", "respondent": "PJM", "respondent-name": "PJM Interconnection, LLC", "type": "DF", "type-name": "Day-ahead demand forecast", "value": "74434", "value-units": "megawatthours"}, {"period": "2024-10-18T08", "respondent": "PJM", "respondent-name": "PJM Interconnection, LLC", "type": "NG", "type-name": "Net generation", "value": "74000", "value-units": "megawatthours"}, {"period": "2024-10-18T08", "respondent": "PJM", "respondent-name": "PJM Interconnection, LLC", "type": "TI", "type-name": "Total interchange", "value": "-518", "value-units": "megawatthours"}, {"period": "2024-10-18T09", "respondent": "PJM", "respondent-name": "PJM Interconnection, LLC", "type": "D", "type-name": "Demand", "value": "75747", "value-units": "megawatthours"}, {"period": "2024-10-18T09", "respondent": "PJM", "respondent-name": "PJM Interconnection, LLC", "type": "DF", "type-name": "Day-ahead demand forecast", "value": "78553", "value-units": "megawatthours"}, {"period": "2024-10-18T09", "respondent": "PJM", "respondent-name": "PJM Interconnection, LLC", "type": "NG", "type-name": "Net generation", "value": "75189", "value-units": "megawatthours"}, {"period": "2024-10-18T09", "respondent": "PJM", "respondent-name": "PJM Interconnection, LLC", "type": "TI", "type-name": "Total interchange", "value": "-558", "value-units": "megawatthours"}, {"period": "2024-10-18T10", "respondent": "PJM", "respondent-name": "PJM Interconnection, LLC", "type": "D", "type-name": "Demand", "value": "79054", "value-units": "megawatthours"}, {"period": "2024-10-18T10", "respondent": "PJM", "respondent-name": "PJM Interconnection, LLC", "type": "DF", "type-name": "Day-ahead demand forecast", "value": "84847", "value-units": "megawatthours"}, {"period": "2024-10-18T10", "respondent": "PJM", "respondent-name": "PJM Interconnection, LLC", "type": "NG", "type-name": "Net generation", "value": "78130", "value-units": "megawatthours"}, {"period": "2024-10-18T10", "respondent": "PJM", "respondent-name": "PJM Interconnection, LLC", "type": "TI", "type-name": "Total interchange", "value": "-924", "value-units": "megawatthours"}, {"period": "2024-10-18T11", "respondent": "PJM", "respondent-name": "PJM Interconnection, LLC", "type": "D", "type-name": "Demand", "value": "85587", "value-units": "megawatthours"}, {"period": "2024-10-18T11", "respondent": "PJM", "respondent-name": "PJM Interconnection, LLC", "type": "DF", "type-name": "Day-ahead demand forecast", "value": "88504", "value-units": "megawatthours"}, {"period": "2024-10-18T11", "respondent": "PJM", "respondent-name": "PJM Interconnection, LLC", "type": "NG", "type-name": "Net generation", "value": "84058", "value-units": "megawatthours"}, {"period": "2024-10-18T11", "respondent": "PJM", "respondent-name": "PJM Interconnection, LLC", "type": "TI", "type-name": "Total interchange", "value": "-1529", "value-units": "megawatthours"}, {"period": "2024-10-18T12", "respondent": "PJM", "respondent-name": "PJM Interconnection, LLC", "type": "D", "type-name": "Demand", "value": "90024", "value-units": "megawatthours"}, {"period": "2024-10-18T12", "respondent": "PJM", "respondent-name": "PJM Interconnection, LLC", "type": "DF", "type-name": "Day-ahead demand forecast", "value": "87790", "value-units": "megawatthours"}, {"period": "2024-10-18T12", "respondent": "PJM", "respondent-name": "PJM Interconnection, LLC", "type": "NG", "type-name": "Net generation", "value": "87502", "value-units": "megawatthours"}, {"period": "2024-10-18T12", "respondent": "PJM", "respondent-name": "PJM Interconnection, LLC", "type": "TI", "type-name": "Total interchange", "value": "-2522", "value-units": "megawatthours"}, {"period": "2024-10-18T13", "respondent": "PJM", "respondent-name": "PJM Interconnection, LLC", "type": "D", "type-name": "Demand", "value": "90123", "value-units": "megawatthours"}, {"period": "2024-10-18T13", "respondent": "PJM", "respondent-name": "PJM Interconnection, LLC", "type": "DF", "type-name": "Day-ahead demand forecast", "value": "85048", "value-units": "megawatthours"}, {"period": "2024-10-18T13", "respondent": "PJM", "respondent-name": "PJM Interconnection, LLC", "type": "NG", "type-name": "Net generation", "value": "88953", "value-units": "megawatthours"}, {"period": "2024-10-18T13", "respondent": "PJM", "respondent-name": "PJM Interconnection, LLC", "type": "TI", "type-name": "Total interchange", "value": "-1170", "value-units": "megawatthours"}, {"period": "2024-10-18T14", "respondent": "PJM", "respondent-name": "PJM Interconnection, LLC", "type": "D", "type-name": "Demand", "value": "87666", "value-units": "megawatthours"}, {"period": "2024-10-18T14", "respondent": "PJM", "respondent-name": "PJM Interconnection, LLC", "type": "DF", "type-name": "Day-ahead demand forecast", "value": "82748", "value-units": "megawatthours"}, {"period": "2024-10-18T14", "respondent": "PJM", "respondent-name": "PJM Interconnection, LLC", "type": "NG", "type-name": "Net generation", "value": "86874", "value-units": "megawatthours"}, {"period": "2024-10-18T14", "respondent": "PJM", "respondent-name": "PJM Interconnection, LLC", "type": "TI", "type-name": "Total interchange", "value": "-793", "value-units": "megawatthours"}, {"period": "2024-10-18T15", "respondent": "PJM", "respondent-name": "PJM Interconnection, LLC", "type": "D", "type-name": "Demand", "value": "85314", "value-units": "megawatthours"}, {"period": "2024-10-18T15", "respondent": "PJM", "respondent-name": "PJM Interconnection, LLC", "type": "DF", "type-name": "Day-ahead demand forecast", "value": "81004", "value-units": "megawatthours"}, {"period": "2024-10-18T15", "respondent": "PJM", "respondent-name": "PJM Interconnection, LLC", "type": "NG", "type-name": "Net generation", "value": "85065", "value-units": "megawatthours"}, {"period": "2024-10-18T15", "respondent": "PJM", "respondent-name": "PJM Interconnection, LLC", "type": "TI", "type-name": "Total interchange", "value": "-250", "value-units": "megawatthours"}, {"period": "2024-10-18T16", "respondent": "PJM", "respondent-name": "PJM Interconnection, LLC", "type": "D", "type-name": "Demand", "value": "83160", "value-units": "megawatthours"}, {"period": "2024-10-18T16", "respondent": "PJM", "respondent-name": "PJM Interconnection, LLC", "type": "DF", "type-name": "Day-ahead demand forecast", "value": "79864", "value-units": "megawatthours"}, {"period": "2024-10-18T16", "respondent": "PJM", "respondent-name": "PJM Interconnection, LLC", "type": "NG", "type-name": "Net generation", "value": "83320", "value-units": "megawatthours"}, {"period": "2024-10-18T16", "respondent": "PJM", "respondent-name": "PJM Interconnection, LLC", "type": "TI", "type-name": "Total interchange", "value": "159", "value-units": "megawatthours"}, {"period": "2024-10-18T17", "respondent": "PJM", "respondent-name": "PJM Interconnection, LLC", "type": "D", "type-name": "Demand", "value": "82250", "value-units": "megawatthours"}, {"period": "2024-10-18T17", "respondent": "PJM", "respondent-name": "PJM Interconnection, LLC", "type": "DF", "type-name": "Day-ahead demand forecast", "value": "79277", "value-units": "megawatthours"}, {"period": "2024-10-18T17", "respondent": "PJM", "respondent-name": "PJM Interconnection, LLC", "type": "NG", "type-name": "Net generation", "value": "82637", "value-units": "megawatthours"}, {"period": "2024-10-18T17", "respondent": "PJM", "respondent-name": "PJM Interconnection, LLC", "type": "TI", "type-name": "Total interchange", "value": "388", "value-units": "megawatthours"}, {"period": "2024-10-18T18", "respondent": "PJM", "respondent-name": "PJM Interconnection, LLC", "type": "D", "type-name": "Demand", "value": "81737", "value-units": "megawatthours"}, {"period": "2024-10-18T18", "respondent": "PJM", "respondent-name": "PJM Interconnection, LLC", "type": "DF", "type-name": "Day-ahead demand forecast", "value": "78811", "value-units": "megawatthours"}, {"period": "2024-10-18T18", "respondent": "PJM", "respondent-name": "PJM Interconnection, LLC", "type": "NG", "type-name": "Net generation", "value": "82669", "value-units": "megawatthours"}, {"period": "2024-10-18T18", "respondent": "PJM", "respondent-name": "PJM Interconnection, LLC", "type": "TI", "type-name": "Total interchange", "value": "932", "value-units": "megawatthours"}, {"period": "2024-10-18T19", "respondent": "PJM", "respondent-name": "PJM Interconnection, LLC", "type": "D", "type-name": "Demand", "value": "81601", "value-units": "megawatthours"}, {"period": "2024-10-18T19", "respondent": "PJM", "respondent-name": "PJM Interconnection, LLC", "type": "DF", "type-name": "Day-ahead demand forecast", "value": "78622", "value-units": "megawatthours"}, {"period": "2024-10-18T19", "respondent": "PJM", "respondent-name": "PJM Interconnection, LLC", "type": "NG", "type-name": "Net generation", "value": "82200", "value-units": "megawatthours"}, {"period": "2024-10-18T19", "respondent": "PJM", "respondent-name": "PJM Interconnection, LLC", "type": "TI", "type-name": "Total interchange", "value": "599", "value-units": "megawatthours"}, {"period": "2024-10-18T20", "respondent": "PJM", "respondent-name": "PJM Interconnection, LLC", "type": "D", "type-name": "Demand", "value": "81956", "value-units": "megawatthours"}, {"period": "2024-10-18T20", "respondent": "PJM", "respondent-name": "PJM Interconnection, LLC", "type": "DF", "type-name": "Day-ahead demand forecast", "value": "79391", "value-units": "megawatthours"}, {"period": "2024-10-18T20", "respondent": "PJM", "respondent-name": "PJM Interconnection, LLC", "type": "NG", "type-name": "Net generation", "value": "82930", "value-units": "megawatthours"}, {"period": "2024-10-18T20", "respondent": "PJM", "respondent-name": "PJM Interconnection, LLC", "type": "TI", "type-name": "Total interchange", "value": "975", "value-units": "megawatthours"}, {"period": "2024-10-18T21", "respondent": "PJM", "respondent-name": "PJM Interconnection, LLC", "type": "D", "type-name": "Demand", "value": "82417", "value-units": "megawatthours"}, {"period": "2024-10-18T21", "respondent": "PJM", "respondent-name": "PJM Interconnection, LLC", "type": "DF", "type-name": "Day-ahead demand forecast", "value": "80451", "value-units": "megawatthours"}, {"period": "2024-10-18T21", "respondent": "PJM", "respondent-name": "PJM Interconnection, LLC", "type": "NG", "type-name": "Net generation", "value": "83350", "value-units": "megawatthours"}, {"period": "2024-10-18T21", "respondent": "PJM", "respondent-name": "PJM Interconnection, LLC", "type": "TI", "type-name": "Total interchange", "value": "933", "value-units": "megawatthours"}, {"period": "2024-10-18T22", "respondent": "PJM", "respondent-name": "PJM Interconnection, LLC", "type": "D", "type-name": "Demand", "value": "83010", "value-units": "megawatthours"}, {"period": "2024-10-18T22", "respondent": "PJM", "respondent-name": "PJM Interconnection, LLC", "type": "DF", "type-name": "Day-ahead demand forecast", "value": "81028", "value-units": "megawatthours"}, {"period": "2024-10-18T22", "respondent": "PJM", "respondent-name": "PJM Interconnection, LLC", "type": "NG", "type-name": "Net generation", "value": "83647", "value-units": "megawatthours"}, {"period": "2024-10-18T22", "respondent": "PJM", "respondent-name": "PJM Interconnection, LLC", "type": "TI", "type-name": "Total interchange", "value": "637", "value-units": "megawatthours"}, {"period": "2024-10-18T23", "respondent": "PJM", "respondent-name": "PJM Interconnection, LLC", "type": "D", "type-name": "Demand", "value": "83991", "value-units": "megawatthours"}, {"period": "2024-10-18T23", "respondent": "PJM", "respondent-name": "PJM Interconnection, LLC", "type": "DF", "type-name": "Day-ahead demand forecast", "value": "82103", "value-units": "megawatthours"}, {"period": "2024-10-18T23", "respondent": "PJM", "respondent-name": "PJM Interconnection, LLC", "type": "NG", "type-name": "Net generation", "value": "83426", "value-units": "megawatthours"}, {"period": "2024-10-18T23", "respondent": "PJM", "respondent-name": "PJM Interconnection, LLC", "type": "TI", "type-name": "Total interchange", "value": "-564", "value-units": "megawatthours"}, {"period": "2024-10-19T00", "respondent": "PJM", "respondent-name": "PJM Interconnection, LLC", "type": "D", "type-name": "Demand", "value": "84789", "value-units": "megawatthours"}, {"period": "2024-10-19T00", "respondent": "PJM", "respondent-name": "PJM Interconnection, LLC", "type": "DF", "type-name": "Day-ahead demand forecast", "value": "82736", "value-units": "megawatthours"}, {"period": "2024-10-19T00", "respondent": "PJM", "respondent-name": "PJM Interconnection, LLC", "type": "NG", "type-name": "Net generation", "value": "83022", "value-units": "megawatthours"}, {"period": "2024-10-19T00", "respondent": "PJM", "respondent-name": "PJM Interconnection, LLC", "type": "TI", "type-name": "Total interchange", "value": "-1767", "value-units": "megawatthours"}, {"period": "2024-10-19T01", "respondent": "PJM", "respondent-name": "PJM Interconnection, LLC", "type": "D", "type-name": "Demand", "value": "83385", "value-units": "megawatthours"}, {"period": "2024-10-19T01", "respondent": "PJM", "respondent-name": "PJM Interconnection, LLC", "type": "DF", "type-name": "Day-ahead demand forecast", "value": "81053", "value-units": "megawatthours"}, {"period": "2024-10-19T01", "respondent": "PJM", "respondent-name": "PJM Interconnection, LLC", "type": "NG", "type-name": "Net generation", "value": "81970", "value-units": "megawatthours"}, {"period": "2024-10-19T01", "respondent": "PJM", "respondent-name": "PJM Interconnection, LLC", "type": "TI", "type-name": "Total interchange", "value": "-1414", "value-units": "megawatthours"}, {"period": "2024-10-19T02", "respondent": "PJM", "respondent-name": "PJM Interconnection, LLC", "type": "D", "type-name": "Demand", "value": "81241", "value-units": "megawatthours"}, {"period": "2024-10-19T02", "respondent": "PJM", "respondent-name": "PJM Interconnection, LLC", "type": "DF", "type-name": "Day-ahead demand forecast", "value": "77859", "value-units": "megawatthours"}, {"period": "2024-10-19T02", "respondent": "PJM", "respondent-name": "PJM Interconnection, LLC", "type": "NG", "type-name": "Net generation", "value": "80360", "value-units": "megawatthours"}, {"period": "2024-10-19T02", "respondent": "PJM", "respondent-name": "PJM Interconnection, LLC", "type": "TI", "type-name": "Total interchange", "value": "-881", "value-units": "megawatthours"}, {"period": "2024-10-19T03", "respondent": "PJM", "respondent-name": "PJM Interconnection, LLC", "type": "D", "type-name": "Demand", "value": "78294", "value-units": "megawatthours"}, {"period": "2024-10-19T03", "respondent": "PJM", "respondent-name": "PJM Interconnection, LLC", "type": "DF", "type-name": "Day-ahead demand forecast", "value": "74317", "value-units": "megawatthours"}, {"period": "2024-10-19T03", "respondent": "PJM", "respondent-name": "PJM Interconnection, LLC", "type": "NG", "type-name": "Net generation", "value": "78473", "value-units": "megawatthours"}, {"period": "2024-10-19T03", "respondent": "PJM", "respondent-name": "PJM Interconnection, LLC", "type": "TI", "type-name": "Total interchange", "value": "179", "value-units": "megawatthours"}, {"period": "2024-10-19T04", "respondent": "PJM", "respondent-name": "PJM Interconnection, LLC", "type": "D", "type-name": "Demand", "value": "75358", "value-units": "megawatthours"}, {"period": "2024-10-19T04", "respondent": "PJM", "respondent-name": "PJM Interconnection, LLC", "type": "DF", "type-name": "Day-ahead demand forecast", "value": "71066", "value-units": "megawatthours"}, {"period": "2024-10-19T04", "respondent": "PJM", "respondent-name": "PJM Interconnection, LLC", "type": "NG", "type-name": "Net generation", "value": "75742", "value-units": "megawatthours"}, {"period": "2024-10-19T04", "respondent": "PJM", "respondent-name": "PJM Interconnection, LLC", "type": "TI", "type-name": "Total interchange", "value": "385", "value-units": "megawatthours"}, {"period": "2024-10-19T05", "respondent": "PJM", "respondent-name": "PJM Interconnection, LLC", "type": "D", "type-name": "Demand", "value": "72796", "value-units": "megawatthours"}, {"period": "2024-10-19T05", "respondent": "PJM", "respondent-name": "PJM Interconnection, LLC", "type": "DF", "type-name": "Day-ahead demand forecast", "value": "68946", "value-units": "megawatthours"}, {"period": "2024-10-19T05", "respondent": "PJM", "respondent-name": "PJM Interconnection, LLC", "type": "NG", "type-name": "Net generation", "value": "72617", "value-units": "megawatthours"}, {"period": "2024-10-19T05", "respondent": "PJM", "respondent-name": "PJM Interconnection, LLC", "type": "TI", "type-name": "Total interchange", "value": "-179", "value-units": "megawatthours"}, {"period": "2024-10-19T06", "respondent": "PJM", "respondent-name": "PJM Interconnection, LLC", "type": "D", "type-name": "Demand", "value": "71658", "value-units": "megawatthours"}, {"period": "2024-10-19T06", "respondent": "PJM", "respondent-name": "PJM Interconnection, LLC", "type": "DF", "type-name": "Day-ahead demand forecast", "value": "67947", "value-units": "megawatthours"}, {"period": "2024-10-19T06", "respondent": "PJM", "respondent-name": "PJM Interconnection, LLC", "type": "NG", "type-name": "Net generation", "value": "72046", "value-units": "megawatthours"}, {"period": "2024-10-19T06", "respondent": "PJM", "respondent-name": "PJM Interconnection, LLC", "type": "TI", "type-name": "Total interchange", "value": "388", "value-units": "megawatthours"}, {"period": "2024-10-19T07", "respondent": "PJM", "respondent-name": "PJM Interconnection, LLC", "type": "D", "type-name": "Demand", "value": "70973", "value-units": "megawatthours"}, {"period": "2024-10-19T07", "respondent": "PJM", "respondent-name": "PJM Interconnection, LLC", "type": "DF", "type-name": "Day-ahead demand forecast", "value": "67678", "value-units": "megawatthours"}, {"period": "2024-10-19T07", "respondent": "PJM", "respondent-name": "PJM Interconnection, LLC", "type": "NG", "type-name": "Net generation", "value": "71022", "value-units": "megawatthours"}, {"period": "2024-10-19T07", "respondent": "PJM", "respondent-name": "PJM Interconnection, LLC", "type": "TI", "type-name": "Total interchange", "value": "49", "value-units": "megawatthours"}, {"period": "2024-10-19T08", "respondent": "PJM", "respondent-name": "PJM Interconnection, LLC", "type": "D", "type-name": "Demand", "value": "70604", "value-units": "megawatthours"}, {"period": "2024-10-19T08", "respondent": "PJM", "respondent-name": "PJM Interconnection, LLC", "type": "DF", "type-name": "Day-ahead demand forecast", "value": "68230", "value-units": "megawatthours"}, {"period": "2024-10-19T08", "respondent": "PJM", "respondent-name": "PJM Interconnection, LLC", "type": "NG", "type-name": "Net generation", "value": "70981", "value-units": "megawatthours"}, {"period": "2024-10-19T08", "respondent": "PJM", "respondent-name": "PJM Interconnection, LLC", "type": "TI", "type-name": "Total interchange", "value": "376", "value-units": "megawatthours"}, {"period": "2024-10-19T09", "respondent": "PJM", "respondent-name": "PJM Interconnection, LLC", "type": "D", "type-name": "Demand", "value": "71213", "value-units": "megawatthours"}, {"period": "2024-10-19T09", "respondent": "PJM", "respondent-name": "PJM Interconnection, LLC", "type": "DF", "type-name": "Day-ahead demand forecast", "value": "70005", "value-units": "megawatthours"}, {"period": "2024-10-19T09", "respondent": "PJM", "respondent-name": "PJM Interconnection, LLC", "type": "NG", "type-name": "Net generation", "value": "71090", "value-units": "megawatthours"}, {"period": "2024-10-19T09", "respondent": "PJM", "respondent-name": "PJM Interconnection, LLC", "type": "TI", "type-name": "Total interchange", "value": "-123", "value-units": "megawatthours"}, {"period": "2024-10-19T10", "respondent": "PJM", "respondent-name": "PJM Interconnection, LLC", "type": "D", "type-name": "Demand", "value": "72570", "value-units": "megawatthours"}, {"period": "2024-10-19T10", "respondent": "PJM", "respondent-name": "PJM Interconnection, LLC", "type": "DF", "type-name": "Day-ahead demand forecast", "value": "72788", "value-units": "megawatthours"}, {"period": "2024-10-19T10", "respondent": "PJM", "respondent-name": "PJM Interconnection, LLC", "type": "NG", "type-name": "Net generation", "value": "72261", "value-units": "megawatthours"}, {"period": "2024-10-19T10", "respondent": "PJM", "respondent-name": "PJM Interconnection, LLC", "type": "TI", "type-name": "Total interchange", "value": "-310", "value-units": "megawatthours"}, {"period": "2024-10-19T11", "respondent": "PJM", "respondent-name": "PJM Interconnection, LLC", "type": "D", "type-name": "Demand", "value": "75011", "value-units": "megawatthours"}, {"period": "2024-10-19T11", "respondent": "PJM", "respondent-name": "PJM Interconnection, LLC", "type": "DF", "type-name": "Day-ahead demand forecast", "value": "75028", "value-units": "megawatthours"}, {"period": "2024-10-19T11", "respondent": "PJM", "respondent-name": "PJM Interconnection, LLC", "type": "NG", "type-name": "Net generation", "value": "73746", "value-units": "megawatthours"}, {"period": "2024-10-19T11", "respondent": "PJM", "respondent-name": "PJM Interconnection, LLC", "type": "TI", "type-name": "Total interchange", "value": "-1265", "value-units": "megawatthours"}, {"period": "2024-10-19T12", "respondent": "PJM", "respondent-name": "PJM Interconnection, LLC", "type": "D", "type-name": "Demand", "value": "78491", "value-units": "megawatthours"}, {"period": "2024-10-19T12", "respondent": "PJM", "respondent-name": "PJM Interconnection, LLC", "type": "DF", "type-name": "Day-ahead demand forecast", "value": "75988", "value-units": "megawatthours"}, {"period": "2024-10-19T12", "respondent": "PJM", "respondent-name": "PJM Interconnection, LLC", "type": "NG", "type-name": "Net generation", "value": "76250", "value-units": "megawatthours"}, {"period": "2024-10-19T12", "respondent": "PJM", "respondent-name": "PJM Interconnection, LLC", "type": "TI", "type-name": "Total interchange", "value": "-2241", "value-units": "megawatthours"}, {"period": "2024-10-19T13", "respondent": "PJM", "respondent-name": "PJM Interconnection, LLC", "type": "D", "type-name": "Demand", "value": "79694", "value-units": "megawatthours"}, {"period": "2024-10-19T13", "respondent": "PJM", "respondent-name": "PJM Interconnection, LLC", "type": "DF", "type-name": "Day-ahead demand forecast", "value": "75323", "value-units": "megawatthours"}, {"period": "2024-10-19T13", "respondent": "PJM", "respondent-name": "PJM Interconnection, LLC", "type": "NG", "type-name": "Net generation", "value": "78444", "value-units": "megawatthours"}, {"period": "2024-10-19T13", "respondent": "PJM", "respondent-name": "PJM Interconnection, LLC", "type": "TI", "type-name": "Total interchange", "value": "-1250", "value-units": "megawatthours"}, {"period": "2024-10-19T14", "respondent": "PJM", "respondent-name": "PJM Interconnection, LLC", "type": "D", "type-name": "Demand", "value": "79345", "value-units": "megawatthours"}, {"period": "2024-10-19T14", "respondent": "PJM", "respondent-name": "PJM Interconnection, LLC", "type": "DF", "type-name": "Day-ahead demand forecast", "value": "74145", "value-units": "megawatthours"}, {"period": "2024-10-19T14", "respondent": "PJM", "respondent-name": "PJM Interconnection, LLC", "type": "NG", "type-name": "Net generation", "value": "79193", "value-units": "megawatthours"}, {"period": "2024-10-19T14", "respondent": "PJM", "respondent-name": "PJM Interconnection, LLC", "type": "TI", "type-name": "Total interchange", "value": "-153", "value-units": "megawatthours"}, {"period": "2024-10-19T15", "respondent": "PJM", "respondent-name": "PJM Interconnection, LLC", "type": "D", "type-name": "Demand", "value": "77464", "value-units": "megawatthours"}, {"period": "2024-10-19T15", "respondent": "PJM", "respondent-name": "PJM Interconnection, LLC", "type": "DF", "type-name": "Day-ahead demand forecast", "value": "73071", "value-units": "megawatthours"}, {"period": "2024-10-19T15", "respondent": "PJM", "respondent-name": "PJM Interconnection, LLC", "type": "NG", "type-name": "Net generation", "value": "78490", "value-units": "megawatthours"}, {"period": "2024-10-19T15", "respondent": "PJM", "respondent-name": "PJM Interconnection, LLC", "type": "TI", "type-name": "Total interchange", "value": "1026", "value-units": "megawatthours"}, {"period": "2024-10-19T16", "respondent": "PJM", "respondent-name": "PJM Interconnection, LLC", "type": "D", "type-name": "Demand", "value": "76108", "value-units": "megawatthours"}, {"period": "2024-10-19T16", "respondent": "PJM", "respondent-name": "PJM Interconnection, LLC", "type": "DF", "type-name": "Day-ahead demand forecast", "value": "72315", "value-units": "megawatthours"}, {"period": "2024-10-19T16", "respondent": "PJM", "respondent-name": "PJM Interconnection, LLC", "type": "NG", "type-name": "Net generation", "value": "77962", "value-units": "megawatthours"}, {"period": "2024-10-19T16", "respondent": "PJM", "respondent-name": "PJM Interconnection, LLC", "type": "TI", "type-name": "Total interchange", "value": "1854", "value-units": "megawatthours"}, {"period": "2024-10-19T17", "respondent": "PJM", "respondent-name": "PJM Interconnection, LLC", "type": "D", "type-name": "Demand", "value": "75065", "value-units": "megawatthours"}, {"period": "2024-10-19T17", "respondent": "PJM", "respondent-name": "PJM Interconnection, LLC", "type": "DF", "type-name": "Day-ahead demand forecast", "value": "71803", "value-units": "megawatthours"}, {"period": "2024-10-19T17", "respondent": "PJM", "respondent-name": "PJM Interconnection, LLC", "type": "NG", "type-name": "Net generation", "value": "76932", "value-units": "megawatthours"}, {"period": "2024-10-19T17", "respondent": "PJM", "respondent-name": "PJM Interconnection, LLC", "type": "TI", "type-name": "Total interchange", "value": "1867", "value-units": "megawatthours"}, {"period": "2024-10-19T18", "respondent": "PJM", "respondent-name": "PJM Interconnection, LLC", "type": "D", "type-name": "Demand", "value": "74327", "value-units": "megawatthours"}, {"period": "2024-10-19T18", "respondent": "PJM", "respondent-name": "PJM Interconnection, LLC", "type": "DF", "type-name": "Day-ahead demand forecast", "value": "71695", "value-units": "megawatthours"}, {"period": "2024-10-19T18", "respondent": "PJM", "respondent-name": "PJM Interconnection, LLC", "type": "NG", "type-name": "Net generation", "value": "76268", "value-units": "megawatthours"}, {"period": "2024-10-19T18", "respondent": "PJM", "respondent-name": "PJM Interconnection, LLC", "type": "TI", "type-name": "Total interchange", "value": "1941", "value-units": "megawatthours"}, {"period": "2024-10-19T19", "respondent": "PJM", "respondent-name": "PJM Interconnection, LLC", "type": "D", "type-name": "Demand", "value": "74476", "value-units": "megawatthours"}, {"period": "2024-10-19T19", "respondent": "PJM", "respondent-name": "PJM Interconnection, LLC", "type": "DF", "type-name": "Day-ahead demand forecast", "value": "72181", "value-units": "megawatthours"}, {"period": "2024-10-19T19", "respondent": "PJM", "respondent-name": "PJM Interconnection, LLC", "type": "NG", "type-name": "Net generation", "value": "76631", "value-units": "megawatthours"}, {"period": "2024-10-19T19", "respondent": "PJM", "respondent-name": "PJM Interconnection, LLC", "type": "TI", "type-name": "Total interchange", "value": "2155", "value-units": "megawatthours"}, {"period": "2024-10-19T20", "respondent": "PJM", "respondent-name": "PJM Interconnection, LLC", "type": "D", "type-name": "Demand", "value": "75587", "value-units": "megawatthours"}, {"period": "2024-10-19T20", "respondent": "PJM", "respondent-name": "PJM Interconnection, LLC", "type": "DF", "type-name": "Day-ahead demand forecast", "value": "73445", "value-units": "megawatthours"}, {"period": "2024-10-19T20", "respondent": "PJM", "respondent-name": "PJM Interconnection, LLC", "type": "NG", "type-name": "Net generation", "value": "78319", "value-units": "megawatthours"}, {"period": "2024-10-19T20", "respondent": "PJM", "respondent-name": "PJM Interconnection, LLC", "type": "TI", "type-name": "Total interchange", "value": "2731", "value-units": "megawatthours"}, {"period": "2024-10-19T21", "respondent": "PJM", "respondent-name": "PJM Interconnection, LLC", "type": "D", "type-name": "Demand", "value": "77016", "value-units": "megawatthours"}, {"period": "2024-10-19T21", "respondent": "PJM", "respondent-name": "PJM Interconnection, LLC", "type": "DF", "type-name": "Day-ahead demand forecast", "value": "75155", "value-units": "megawatthours"}, {"period": "2024-10-19T21", "respondent": "PJM", "respondent-name": "PJM Interconnection, LLC", "type": "NG", "type-name": "Net generation", "value": "78914", "value-units": "megawatthours"}, {"period": "2024-10-19T21", "respondent": "PJM", "respondent-name": "PJM Interconnection, LLC", "type": "TI", "type-name": "Total interchange", "value": "1898", "value-units": "megawatthours"}, {"period": "2024-10-19T22", "respondent": "PJM", "respondent-name": "PJM Interconnection, LLC", "type": "D", "type-name": "Demand", "value": "77672", "value-units": "megawatthours"}, {"period": "2024-10-19T22", "respondent": "PJM", "respondent-name": "PJM Interconnection, LLC", "type": "DF", "type-name": "Day-ahead demand forecast", "value": "76201", "value-units": "megawatthours"}, {"period": "2024-10-19T22", "respondent": "PJM", "respondent-name": "PJM Interconnection, LLC", "type": "NG", "type-name": "Net generation", "value": "78201", "value-units": "megawatthours"}, {"period": "2024-10-19T22", "respondent": "PJM", "respondent-name": "PJM Interconnection, LLC", "type": "TI", "type-name": "Total interchange", "value": "528", "value-units": "megawatthours"}, {"period": "2024-10-19T23", "respondent": "PJM", "respondent-name": "PJM Interconnection, LLC", "type": "D", "type-name": "Demand", "value": "79099", "value-units": "megawatthours"}, {"period": "2024-10-19T23", "respondent": "PJM", "respondent-name": "PJM Interconnection, LLC", "type": "DF", "type-name": "Day-ahead demand forecast", "value": "77578", "value-units": "megawatthours"}, {"period": "2024-10-19T23", "respondent": "PJM", "respondent-name": "PJM Interconnection, LLC", "type": "NG", "type-name": "Net generation", "value": "78584", "value-units": "megawatthours"}, {"period": "2024-10-19T23", "respondent": "PJM", "respondent-name": "PJM Interconnection, LLC", "type": "TI", "type-name": "Total interchange", "value": "-515", "value-units": "megawatthours"}, {"period": "2024-10-20T00", "respondent": "PJM", "respondent-name": "PJM Interconnection, LLC", "type": "D", "type-name": "Demand", "value": "79768", "value-units": "megawatthours"}, {"period": "2024-10-20T00", "respondent": "PJM", "respondent-name": "PJM Interconnection, LLC", "type": "DF", "type-name": "Day-ahead demand forecast", "value": "77818", "value-units": "megawatthours"}, {"period": "2024-10-20T00", "respondent": "PJM", "respondent-name": "PJM Interconnection, LLC", "type": "NG", "type-name": "Net generation", "value": "79231", "value-units": "megawatthours"}, {"period": "2024-10-20T00", "respondent": "PJM", "respondent-name": "PJM Interconnection, LLC", "type": "TI", "type-name": "Total interchange", "value": "-538", "value-units": "megawatthours"}], "description": "Hourly demand, day-ahead demand forecast, net generation, and interchange by balancing authority.  \n    Source: Form EIA-930\n    Product: Hourly Electric Grid Monitor"}, "request": {"command": "/v2/electricity/rto/region-data/data/", "params": {"api_key": "BzIZMHGubqadkfd0FYFD3ErzmKGfRlZepHZYbTWY", "frequency": "hourly", "data": ["value"], "facets": {"respondent": ["PJM"], "type": ["D", "DF", "NG", "TI"]}, "start": "2024-10-17T00", "end": "2024-10-20T00", "sort": [{"column": "period", "direction": "asc"}], "offset": "0", "length": "5000"}}, "apiVersion": "2.1.7", "ExcelAddInVersion": "2.1.0"}
